djangodollar/__init__.py
djangodollar/apps.py
djangodollar/dollar.py
djangodollar/fields.py
djangodollar/tests.py
djangodollar-0.2.0.dist-info/WHEEL
djangodollar-0.2.0.dist-info/METADATA
djangodollar-0.2.0.dist-info/RECORD
